concepts/CN1.1.json
concepts/__init__.py
concepts/auxiliary_verbs.json
concepts/city.json
concepts/clothes.json
concepts/furniture.json
concepts/health.json
concepts/house.json
concepts/interrogative.json
concepts/linguistics.json
concepts/little_words.json
concepts/money.json
concepts/nature.json
concepts/possessive_adjectives.json
concepts/professions.json
concepts/sentence_types.json
concepts/time.json
concepts/travel.json
concepts/weather.json
concepts/SM/SM1/SM1.1.json
concepts/SM/SM1/SM1.2.json
concepts/SM/SM1/SM1.3.json
concepts/SM/SM1/SM1.4.json
concepts/SM/SM1/SM1.5.json
concepts/SM/SM1/SM1.6.json
concepts/SM/SM1/SM1.7.json
concepts/SM/SM1/SM1.8.json
concepts/SM/SM1/SM1.9.json
concepts/SM/SM2/SM2.1.json
concepts/SM/SM2/SM2.2.json
concepts/SM/SM2/SM2.3.json
concepts/SM/SM2/SM2.4.json
concepts/SM/SM2/SM2.5.json
concepts/SM/SM2/SM2.6.json
concepts/adjectives/active.json
concepts/adjectives/all kinds of.json
concepts/adjectives/awesome.json
concepts/adjectives/bad.json
concepts/adjectives/beautiful.json
concepts/adjectives/big.json
concepts/adjectives/bilingual.json
concepts/adjectives/boring.json
concepts/adjectives/brave.json
concepts/adjectives/bright.json
concepts/adjectives/by.json
concepts/adjectives/cheap.json
concepts/adjectives/cheerful.json
concepts/adjectives/closed.json
concepts/adjectives/cold.json
concepts/adjectives/common.json
concepts/adjectives/comprehensive.json
concepts/adjectives/cool.json
concepts/adjectives/crazy.json
concepts/adjectives/current.json
concepts/adjectives/cute.json
concepts/adjectives/dark.json
concepts/adjectives/dead.json
concepts/adjectives/delicious.json
concepts/adjectives/different.json
concepts/adjectives/distant.json
concepts/adjectives/divorced.json
concepts/adjectives/dry.json
concepts/adjectives/dumb.json
concepts/adjectives/early.json
concepts/adjectives/easy.json
concepts/adjectives/energetic.json
concepts/adjectives/engaged.json
concepts/adjectives/enthusiastic.json
concepts/adjectives/excellent.json
toisto-0.40.2.dist-info/licenses/LICENSE
toisto-0.40.2.dist-info/METADATA
toisto-0.40.2.dist-info/WHEEL
toisto-0.40.2.dist-info/entry_points.txt
toisto-0.40.2.dist-info/top_level.txt
toisto-0.40.2.dist-info/RECORD
