Metadata-Version: 2.4
Name: toisto
Version: 0.40.2
Summary: Toisto is a command-line terminal app to practice languages.
Author-email: Frank Niessink <frank@niessink.com>
License-Expression: Apache-2.0
Project-URL: Changelog, https://github.com/fniessink/toisto/blob/main/CHANGELOG.md
Project-URL: Issues, https://github.com/fniessink/toisto/issues
Project-URL: Repository, https://github.com/fniessink/toisto
Keywords: dutch,english,finnish,language learning
Classifier: Development Status :: 4 - Beta
Classifier: Intended Audience :: End Users/Desktop
Classifier: Natural Language :: English
Classifier: Operating System :: MacOS
Classifier: Operating System :: Microsoft :: Windows
Classifier: Operating System :: POSIX :: Linux
Classifier: Programming Language :: Python
Classifier: Programming Language :: Python :: 3 :: Only
Classifier: Programming Language :: Python :: 3.11
Classifier: Programming Language :: Python :: 3.12
Classifier: Programming Language :: Python :: 3.13
Classifier: Programming Language :: Python :: 3.14
Classifier: Topic :: Education
Requires-Python: <=3.14,>=3.11
License-File: LICENSE
Requires-Dist: dramatic==0.5.0
Requires-Dist: gtts==2.5.4
Requires-Dist: pygame-ce==2.5.6
Requires-Dist: requests>=2.28
Requires-Dist: rich==14.2.0
Requires-Dist: rich-argparse==1.7.1
Provides-Extra: dev
Requires-Dist: bandit==1.8.6; extra == "dev"
Requires-Dist: coverage==7.11.0; extra == "dev"
Requires-Dist: fixit==2.1.0; extra == "dev"
Requires-Dist: gprof2dot==2025.4.14; extra == "dev"
Requires-Dist: green==4.0.2; extra == "dev"
Requires-Dist: mutmut==3.3.1; extra == "dev"
Requires-Dist: mypy==1.18.2; extra == "dev"
Requires-Dist: pyproject-fmt==2.11.0; extra == "dev"
Requires-Dist: ruff==0.14.2; extra == "dev"
Requires-Dist: troml==0.4.1; extra == "dev"
Requires-Dist: types-requests==2.32.4.20250913; extra == "dev"
Requires-Dist: unittest-xml-reporting==3.2.0; extra == "dev"
Requires-Dist: vulture==2.14; extra == "dev"
Dynamic: license-file
